csctracker_queue_scheduler/__init__.py
csctracker_queue_scheduler/models/__init__.py
csctracker_queue_scheduler/models/base_dto.py
csctracker_queue_scheduler/models/generic_data_dto.py
csctracker_queue_scheduler/models/enums/__init__.py
csctracker_queue_scheduler/models/enums/time_unit.py
csctracker_queue_scheduler/services/__init__.py
csctracker_queue_scheduler/services/queue_service.py
csctracker_queue_scheduler/services/scheduler_service.py
csctracker_queue_scheduler/utils/__init__.py
csctracker_queue_scheduler/utils/utils.py
csctracker_queue_scheduler-24.6.1.dist-info/LICENSE
csctracker_queue_scheduler-24.6.1.dist-info/METADATA
csctracker_queue_scheduler-24.6.1.dist-info/WHEEL
csctracker_queue_scheduler-24.6.1.dist-info/top_level.txt
csctracker_queue_scheduler-24.6.1.dist-info/RECORD
