Metadata-Version: 2.1
Name: csctracker-queue-scheduler
Version: 24.6.1
Summary: A library for handle scheduled jobs.
Home-page: https://github.com/krlsedu/CscTrackerQueueScheduler.git
Author: Carlos Eduardo
License: MIT
Keywords: queue,scheduled,scheduler
Platform: UNKNOWN
Classifier: Intended Audience :: Developers
Classifier: Programming Language :: Python :: 3
Classifier: Programming Language :: Python :: 3.9
Classifier: Topic :: Software Development
Requires-Python: >=3
Requires-Dist: pytz ~=2023.3.post1
Requires-Dist: schedule ~=1.2.1
